basic_memory/__init__.py
basic_memory/config.py
basic_memory/db.py
basic_memory/deps.py
basic_memory/file_utils.py
basic_memory/ignore_utils.py
basic_memory/project_resolver.py
basic_memory/runtime.py
basic_memory/utils.py
basic_memory/alembic/alembic.ini
basic_memory/alembic/env.py
basic_memory/alembic/migrations.py
basic_memory/alembic/script.py.mako
basic_memory/alembic/versions/314f1ea54dc4_add_postgres_full_text_search_support_.py
basic_memory/alembic/versions/3dae7c7b1564_initial_schema.py
basic_memory/alembic/versions/502b60eaa905_remove_required_from_entity_permalink.py
basic_memory/alembic/versions/5fe1ab1ccebe_add_projects_table.py
basic_memory/alembic/versions/647e7a75e2cd_project_constraint_fix.py
basic_memory/alembic/versions/6830751f5fb6_merge_multiple_heads.py
basic_memory/alembic/versions/9d9c1cb7d8f5_add_mtime_and_size_columns_to_entity_.py
basic_memory/alembic/versions/a1b2c3d4e5f6_fix_project_foreign_keys.py
basic_memory/alembic/versions/a2b3c4d5e6f7_add_search_index_entity_cascade.py
basic_memory/alembic/versions/b3c3938bacdb_relation_to_name_unique_index.py
basic_memory/alembic/versions/cc7172b46608_update_search_index_schema.py
basic_memory/alembic/versions/e7e1f4367280_add_scan_watermark_tracking_to_project.py
basic_memory/alembic/versions/f8a9b2c3d4e5_add_pg_trgm_for_fuzzy_link_resolution.py
basic_memory/alembic/versions/g9a0b3c4d5e6_add_external_id_to_project_and_entity.py
basic_memory/api/__init__.py
basic_memory/api/app.py
basic_memory/api/container.py
basic_memory/api/template_loader.py
basic_memory/api/routers/__init__.py
basic_memory/api/routers/directory_router.py
basic_memory/api/routers/importer_router.py
basic_memory/api/routers/knowledge_router.py
basic_memory/api/routers/management_router.py
basic_memory/api/routers/memory_router.py
basic_memory/api/routers/project_router.py
basic_memory/api/routers/prompt_router.py
basic_memory/api/routers/resource_router.py
basic_memory/api/routers/search_router.py
basic_memory-0.18.0.dist-info/METADATA
basic_memory-0.18.0.dist-info/WHEEL
basic_memory-0.18.0.dist-info/entry_points.txt
basic_memory-0.18.0.dist-info/licenses/LICENSE
basic_memory-0.18.0.dist-info/RECORD
