Metadata-Version: 2.4
Name: basic-memory
Version: 0.18.0
Summary: Local-first knowledge management combining Zettelkasten with knowledge graphs
Project-URL: Homepage, https://github.com/basicmachines-co/basic-memory
Project-URL: Repository, https://github.com/basicmachines-co/basic-memory
Project-URL: Documentation, https://github.com/basicmachines-co/basic-memory#readme
Author-email: Basic Machines <hello@basic-machines.co>
License: AGPL-3.0-or-later
License-File: LICENSE
Requires-Python: >=3.12
Requires-Dist: aiofiles>=24.1.0
Requires-Dist: aiosqlite>=0.20.0
Requires-Dist: alembic>=1.14.1
Requires-Dist: anyio>=4.10.0
Requires-Dist: asyncpg>=0.30.0
Requires-Dist: dateparser>=1.2.0
Requires-Dist: fastapi[standard]>=0.115.8
Requires-Dist: fastmcp==2.12.3
Requires-Dist: greenlet>=3.1.1
Requires-Dist: httpx>=0.28.0
Requires-Dist: loguru>=0.7.3
Requires-Dist: markdown-it-py>=3.0.0
Requires-Dist: mcp>=1.23.1
Requires-Dist: mdformat-frontmatter>=2.0.8
Requires-Dist: mdformat-gfm>=0.3.7
Requires-Dist: mdformat>=0.7.22
Requires-Dist: nest-asyncio>=1.6.0
Requires-Dist: pillow>=11.1.0
Requires-Dist: psycopg==3.3.1
Requires-Dist: pybars3>=0.9.7
Requires-Dist: pydantic-settings>=2.6.1
Requires-Dist: pydantic[email,timezone]>=2.12.0
Requires-Dist: pyjwt>=2.10.1
Requires-Dist: pyright>=1.1.390
Requires-Dist: pytest-aio>=1.9.0
Requires-Dist: pytest-asyncio>=1.2.0
Requires-Dist: python-dotenv>=1.1.0
Requires-Dist: python-frontmatter>=1.1.0
Requires-Dist: pyyaml>=6.0.1
Requires-Dist: rich>=13.9.4
Requires-Dist: sniffio>=1.3.1
Requires-Dist: sqlalchemy>=2.0.0
Requires-Dist: typer>=0.9.0
Requires-Dist: unidecode>=1.3.8
Requires-Dist: watchfiles>=1.0.4
